axabc/__init__.py
axabc/db/__init__.py
axabc/db/abstract_repo_collector.py
axabc/db/abstract_uow.py
axabc/db/abstract_uowf.py
axabc/db/async_repository.py
axabc/db/async_uow.py
axabc/db/async_uowf.py
axabc/db/base_schemas.py
axabc/db/combined_repository.py
axabc/db/repo_collector.py
axabc/db/session_mapper.py
axabc/db/types.py
axabc/initialization/__init__.py
axabc/initialization/annotation.py
axabc/initialization/autopass.py
axabc/initialization/lazy_collection.py
axabc/logging/__init__.py
axabc/logging/bot_logger.py
axabc/logging/logger_with_id.py
axabc/logging/qualname_logger.py
axabc/logging/simple_file_logger.py
axabc/logging/simple_stream_logger.py
axabc/test/__init__.py
axabc/test/base_async_test.py
axabc/types/__init__.py
axabc/types/type_cheat.py
axabc-0.0.64.dist-info/METADATA
axabc-0.0.64.dist-info/WHEEL
axabc-0.0.64.dist-info/top_level.txt
axabc-0.0.64.dist-info/RECORD
