Metadata-Version: 2.1
Name: axabc
Version: 0.0.64
Summary: library that defines abstractions for some repeated essences
Author: axdjuraev
Author-email: <axdjuraev@gmail.com>
Requires-Dist: uuid >=1.30
Requires-Dist: pydantic >=1.10.4
